fdstools/__init__.py
fdstools/__main__.py
fdstools/fdstools.py
fdstools/data/libraries/ForenSeqA-UAS.ini
fdstools/data/libraries/ForenSeqA.ini
fdstools/data/libraries/ForenSeqB-UAS.ini
fdstools/data/libraries/ForenSeqB.ini
fdstools/data/libraries/ID-OmniSTR.ini
fdstools/data/libraries/PowerSeq46GY.ini
fdstools/lib/__init__.py
fdstools/lib/cli.py
fdstools/lib/io.py
fdstools/lib/library.py
fdstools/lib/noise.py
fdstools/lib/seq.py
fdstools/lib/sg_align.cp310-win_amd64.pyd
fdstools/lib/util.py
fdstools/tools/__init__.py
fdstools/tools/allelefinder.py
fdstools/tools/bganalyse.py
fdstools/tools/bgcorrect.py
fdstools/tools/bgestimate.py
fdstools/tools/bghomraw.py
fdstools/tools/bghomstats.py
fdstools/tools/bgmerge.py
fdstools/tools/bgpredict.py
fdstools/tools/findnewalleles.py
fdstools/tools/libconvert.py
fdstools/tools/library.py
fdstools/tools/mps2ce.py
fdstools/tools/pipeline.py
fdstools/tools/samplestats.py
fdstools/tools/seqconvert.py
fdstools/tools/stuttermark.py
fdstools/tools/stuttermodel.py
fdstools/tools/tssv.py
fdstools/tools/vis.py
fdstools/vis/d3.min.js
fdstools/vis/vega.min.js
fdstools/vis/allelevis/allelevis.json
fdstools/vis/allelevis/index.html
fdstools/vis/bganalysevis/bganalysevis.json
fdstools/vis/bganalysevis/index.html
fdstools/vis/bgrawvis/bgrawvis.json
fdstools/vis/bgrawvis/index.html
fdstools/vis/profilevis/index.html
fdstools/vis/profilevis/profilevis.json
fdstools/vis/samplevis/index.html
fdstools/vis/samplevis/samplevis.json
fdstools/vis/samplevis/warning.svg
fdstools/vis/stuttermodelvis/index.html
fdstools/vis/stuttermodelvis/stuttermodelvis.json
fdstools-2.1.1.dist-info/LICENSE.txt
fdstools-2.1.1.dist-info/LICENSES-3RD-PARTY.txt
fdstools-2.1.1.dist-info/METADATA
fdstools-2.1.1.dist-info/WHEEL
fdstools-2.1.1.dist-info/entry_points.txt
fdstools-2.1.1.dist-info/top_level.txt
fdstools-2.1.1.dist-info/RECORD
