Metadata-Version: 2.1
Name: fdstools
Version: 2.1.1
Summary: Forensic DNA Sequencing Tools
Home-page: https://fdstools.nl
Author: Jerry Hoogenboom
Author-email: jerryhoogenboom@outlook.com
License: GPLv3+
Project-URL: Bug Tracker, https://github.com/Jerrythafast/FDSTools/issues
Project-URL: Source Code, https://github.com/Jerrythafast/FDSTools
Keywords: bioinformatics forensics stutter NGS MPS DNA sequencing STR
Classifier: Programming Language :: Python :: 3
Classifier: License :: OSI Approved :: GNU General Public License v3 or later (GPLv3+)
Classifier: Operating System :: OS Independent
Classifier: Development Status :: 4 - Beta
Classifier: Intended Audience :: Science/Research
Classifier: Intended Audience :: Legal Industry
Classifier: Topic :: Scientific/Engineering :: Bio-Informatics
Requires-Python: >=3.5
License-File: LICENSE.txt
License-File: LICENSES-3RD-PARTY.txt
Requires-Dist: numpy >=1.17
Requires-Dist: strnaming ~=1.2.0
